Workbook

Sheet Sheet4
A3: Salespersons | B3: Total Invoice Amount. | C3: Total Outstanding
A4: Faisal | B4: 453000 | C4: 426000
A5: Radhika | B5: 436000 | C5: 369000
A6: Sara | B6: 520000 | C6: 333000
A7: Moiz | B7: 454000 | C7: 302000
A8: Ahmedd | B8: 342000 | C8: 260000
A9: Supriya | B9: 345000 | C9: 213000
A10: Faiz | B10: 563000 | C10: 143000
A11: Ahmed | B11: 345000 | C11: 100000
A12: Krish | B12: 342000 | C12: 92000
A13: Bilal | B13: 300000 | C13: 49000
A14: Abrahim | B14: 753000 | C14: -227000
A15: Shiv | B15: 560000 | C15: -420000
A16: Grand Total | B16: 5413000 | C16: 1640000

Sheet Sales Data
A1: Invoice No | B1: Invoice Date | C1: Company Name | D1: Salesperson | E1: Region | F1: Total Invoice Amount | G1: Credit Days | H1: Due Date | I1: Amount Received | J1: Outstanding | K1: Overdue | L1: Aging Category
A2: INV001 | B2: 46023 | C2: Al-Habib Traders | D2: Ahmed | E2: Larkana | F2: 150000 | G2: 30 | H2: =B2 + G2 -> 46053 | I2: =SUMIF('Collection Data'!C2:C16,'Sales Data'!A2,'Collection Data'!E2:E16) -> 150000 | J2: =F2-I2 -> 0 | K2: =IF(TODAY() > H2, TODAY() - H2, 0) -> 22 | L2: =IF(K2=0,"Not Due", IF(K2<=30,"0-30 Days", IF(K2<=60,"31-60 Days", "60+ Days"))) -> 0-30 Days
A3: INV002 | B3: 46025 | C3: Pak Electronics | D3: Sara | E3: Lahore | F3: 220000 | G3: 45 | H3: =B3 + G3 -> 46070 | I3: =SUMIF('Collection Data'!C3:C17,'Sales Data'!A3,'Collection Data'!E3:E17) -> 120000 | J3: =F3-I3 -> 100000 | K3: =IF(TODAY() > H3, TODAY() - H3, 0) -> 5 | L3: =IF(K3=0,"Not Due", IF(K3<=30,"0-30 Days", IF(K3<=60,"31-60 Days", "60+ Days"))) -> 0-30 Days
A4: INV003 | B4: 46027 | C4: Metro Wholesale | D4: Bilal | E4: Islamabad | F4: 175000 | G4: 30 | H4: =B4 + G4 -> 46057 | I4: =SUMIF('Collection Data'!C4:C18,'Sales Data'!A4,'Collection Data'!E4:E18) -> 175000 | J4: =F4-I4 -> 0 | K4: =IF(TODAY() > H4, TODAY() - H4, 0) -> 18 | L4: =IF(K4=0,"Not Due", IF(K4<=30,"0-30 Days", IF(K4<=60,"31-60 Days", "60+ Days"))) -> 0-30 Days
A5: INV004 | B5: 46030 | C5: Royal Distributors | D5: Ahmed | E5: Umerkot | F5: 195000 | G5: 15 | H5: =B5 + G5 -> 46045 | I5: 95000 | J5: =F5-I5 -> 100000 | K5: =IF(TODAY() > H5, TODAY() - H5, 0) -> 30 | L5: =IF(K5=0,"Not Due", IF(K5<=30,"0-30 Days", IF(K5<=60,"31-60 Days", "60+ Days"))) -> 0-30 Days
A6: INV005 | B6: 46034 | C6: City Mart | D6: Sara | E6: Lahore | F6: 300000 | G6: 60 | H6: =B6 + G6 -> 46094 | I6: =SUMIF('Collection Data'!C6:C20,'Sales Data'!A6,'Collection Data'!E6:E20) -> 67000 | J6: =F6-I6 -> 233000 | K6: =IF(TODAY() > H6, TODAY() - H6, 0) -> 0 | L6: =IF(K6=0,"Not Due", IF(K6<=30,"0-30 Days", IF(K6<=60,"31-60 Days", "60+ Days"))) -> Not Due
A7: INV006 | B7: 46037 | C7: National Stores | D7: Bilal | E7: Islamabad | F7: 125000 | G7: 30 | H7: =B7 + G7 -> 46067 | I7: =SUMIF('Collection Data'!C7:C21,'Sales Data'!A7,'Collection Data'!E7:E21) -> 76000 | J7: =F7-I7 -> 49000 | K7: =IF(TODAY() > H7, TODAY() - H7, 0) -> 8 | L7: =IF(K7=0,"Not Due", IF(K7<=30,"0-30 Days", IF(K7<=60,"31-60 Days", "60+ Days"))) -> 0-30 Days
A8: INV007 | B8: 46040 | C8: Dawnlance | D8: Supriya | E8: Umerkot | F8: 345000 | G8: 24 | H8: =B8 + G8 -> 46064 | I8: =SUMIF('Collection Data'!C8:C22,'Sales Data'!A8,'Collection Data'!E8:E22) -> 132000 | J8: =F8-I8 -> 213000 | K8: =IF(TODAY() > H8, TODAY() - H8, 0) -> 11 | L8: =IF(K8=0,"Not Due", IF(K8<=30,"0-30 Days", IF(K8<=60,"31-60 Days", "60+ Days"))) -> 0-30 Days
A9: INV008 | B9: 46043 | C9: L.G | D9: Radhika | E9: Larkana | F9: 436000 | G9: 43 | H9: =B9 + G9 -> 46086 | I9: =SUMIF('Collection Data'!C9:C23,'Sales Data'!A9,'Collection Data'!E9:E23) -> 67000 | J9: =F9-I9 -> 369000 | K9: =IF(TODAY() > H9, TODAY() - H9, 0) -> 0 | L9: =IF(K9=0,"Not Due", IF(K9<=30,"0-30 Days", IF(K9<=60,"31-60 Days", "60+ Days"))) -> Not Due
A10: INV009 | B10: 46047 | C10: Quantium | D10: Krish | E10: Hyderabad | F10: 342000 | G10: 32 | H10: =B10 + G10 -> 46079 | I10: =SUMIF('Collection Data'!C10:C24,'Sales Data'!A10,'Collection Data'!E10:E24) -> 250000 | J10: =F10-I10 -> 92000 | K10: =IF(TODAY() > H10, TODAY() - H10, 0) -> 0 | L10: =IF(K10=0,"Not Due", IF(K10<=30,"0-30 Days", IF(K10<=60,"31-60 Days", "60+ Days"))) -> Not Due
A11: INV010 | B11: 46049 | C11: Deloitte | D11: Shiv | E11: Sukkhar | F11: 560000 | G11: 11 | H11: =B11 + G11 -> 46060 | I11: =SUMIF('Collection Data'!C11:C25,'Sales Data'!A11,'Collection Data'!E11:E25) -> 980000 | J11: =F11-I11 -> -420000 | K11: =IF(TODAY() > H11, TODAY() - H11, 0) -> 15 | L11: =IF(K11=0,"Not Due", IF(K11<=30,"0-30 Days", IF(K11<=60,"31-60 Days", "60+ Days"))) -> 0-30 Days
A12: INV011 | B12: 46053 | C12: JP Morgan | D12: Ahmedd | E12: Tandoadam | F12: 342000 | G12: 21 | H12: =B12 + G12 -> 46074 | I12: 82000 | J12: =F12-I12 -> 260000 | K12: =IF(TODAY() > H12, TODAY() - H12, 0) -> 1 | L12: =IF(K12=0,"Not Due", IF(K12<=30,"0-30 Days", IF(K12<=60,"31-60 Days", "60+ Days"))) -> 0-30 Days
A13: INV012 | B13: 46058 | C13: KPMC | D13: Faisal | E13: Hyderabad | F13: 453000 | G13: 42 | H13: =B13 + G13 -> 46100 | I13: 27000 | J13: =F13-I13 -> 426000 | K13: =IF(TODAY() > H13, TODAY() - H13, 0) -> 0 | L13: =IF(K13=0,"Not Due", IF(K13<=30,"0-30 Days", IF(K13<=60,"31-60 Days", "60+ Days"))) -> Not Due
A14: INV013 | B14: 46065 | C14: BCG | D14: Abrahim | E14: Umerkot | F14: 753000 | G14: 35 | H14: =B14 + G14 -> 46100 | I14: 980000 | J14: =F14-I14 -> -227000 | K14: =IF(TODAY() > H14, TODAY() - H14, 0) -> 0 | L14: =IF(K14=0,"Not Due", IF(K14<=30,"0-30 Days", IF(K14<=60,"31-60 Days", "60+ Days"))) -> Not Due
A15: INV014 | B15: 46070 | C15: Kawish | D15: Faiz | E15: Tandoadam | F15: 563000 | G15: 15 | H15: =B15 + G15 -> 46085 | I15: =SUMIF('Collection Data'!C15:C29,'Sales Data'!A15,'Collection Data'!E15:E29) -> 420000 | J15: =F15-I15 -> 143000 | K15: =IF(TODAY() > H15, TODAY() - H15, 0) -> 0 | L15: =IF(K15=0,"Not Due", IF(K15<=30,"0-30 Days", IF(K15<=60,"31-60 Days", "60+ Days"))) -> Not Due
A16: INV015 | B16: 46076 | C16: Pulse | D16: Moiz | E16: Larkana | F16: 454000 | G16: 23 | H16: =B16 + G16 -> 46099 | I16: 152000 | J16: =F16-I16 -> 302000 | K16: =IF(TODAY() > H16, TODAY() - H16, 0) -> 0 | L16: =IF(K16=0,"Not Due", IF(K16<=30,"0-30 Days", IF(K16<=60,"31-60 Days", "60+ Days"))) -> Not Due
I17: =SUM(I2:I16) -> 3773000

Sheet Collection Data
A1: Receipt No | B1: Receipt Date | C1: Invoice No | D1: Customer Name | E1: Amount Received | F1: Payment Mode
A2: RC001 | B2: 46042 | C2: INV001 | D2: Al-Habib Traders | E2: 100000 | F2: Bank Transfer
A3: RC002 | B3: 46047 | C3: INV004 | D3: Royal Distributors | E3: 95000 | F3: Cash
A4: RC003 | B4: 46058 | C4: INV003 | D4: Metro Wholesale | E4: 175000 | F4: Cheque
A5: RC004 | B5: 46063 | C5: INV001 | D5: Al-Habib Traders | E5: 50000 | F5: Bank Transfer
A6: RC005 | B6: 46073 | C6: INV002 | D6: Pak Electronics | E6: 120000 | F6: Cheque
A7: RC006 | B7: 46081 | C7: INV005 | D7: City Mart | E7: 67000 | F7: Bank Transfer
A8: RC007 | B8: 46084 | C8: INV007 | D8: Dawnlance | E8: 132000 | F8: Cash
A9: RC008 | B9: 46093 | C9: INV006 | D9: National Stores | E9: 76000 | F9: Cheque
A10: RC009 | B10: 46100 | C10: INV011 | D10: JP Morgan | E10: 82000 | F10: Cash
A11: RC010 | B11: 46106 | C11: INV015 | D11: Pulse | E11: 152000 | F11: Online Transfer
A12: RC011 | B12: 46110 | C12: INV012 | D12: KPMC | E12: 27000 | F12: Bank Transfer
A13: RC012 | B13: 46115 | C13: INV008 | D13: L.G | E13: 67000 | F13: Cash
... A16: RC015 | B16: 46131 | C16: INV014 | D16: Kawish | E16: 420000 | F16: Online Transfer

Sheet Collection Summary Report
A1: Collection Report Summary
A2: Months: 01-Jan-2026 to 01-Apr-2026
A5: Category | B5: Amount
A6: Total Sales | B6: =SUM('Sales Data'!F2:F16) -> 5413000
A7: Total Collection | B7: =SUM('Collection Data'!E2:E16) -> 2793000
A8: Outstanding Amount | B8: =B6-B7 -> 2620000
A9: Collection % | B9: =B7/B6 -> 0.51598005
A10: Highest Region Outstanding | B10: Larkana
A11: Hightest Outstanding Salesperson | B11: Faisal
A14: Salesperson-wise Outstanding
A15: Salespersons | B15: Total Invoice Amount. | C15: Total Outstanding
A16: Faisal | B16: 453000 | C16: 426000
A17: Radhika | B17: 436000 | C17: 369000
A18: Sara | B18: 520000 | C18: 333000
A19: Moiz | B19: 454000 | C19: 302000
A20: Ahmedd | B20: 342000 | C20: 260000
A21: Supriya | B21: 345000 | C21: 213000
A22: Faiz | B22: 563000 | C22: 143000
A23: Ahmed | B23: 345000 | C23: 100000
A24: Krish | B24: 342000 | C24: 92000
A25: Bilal | B25: 300000 | C25: 49000
A26: Abrahim | B26: 753000 | C26: -227000
A27: Shiv | B27: 560000 | C27: -420000
A28: Grand Total | B28: 5413000 | C28: 1640000
A30: Region-wise Outstanding
A31: Salespersons | B31: Total Invoice Amount. | C31: Total Outstanding
A32: Larkana | B32: 1040000 | C32: 671000
A33: Hyderabad | B33: 795000 | C33: 518000
A34: Tandoadam | B34: 905000 | C34: 403000
A35: Lahore | B35: 520000 | C35: 333000
A36: Umerkot | B36: 1293000 | C36: 86000
A37: Islamabad | B37: 300000 | C37: 49000
A38: Sukkhar | B38: 560000 | C38: -420000
A39: Grand Total | B39: 5413000 | C39: 1640000
